galaxy_library_maker-0.0.1.data/scripts/get-datatypes.py
galaxy_library_maker-0.0.1.data/scripts/load-into-galaxy-library.py
library/__init__.py
library/tests/__init__.py
library/tests/test_library.py
galaxy_library_maker-0.0.1.dist-info/METADATA
galaxy_library_maker-0.0.1.dist-info/WHEEL
galaxy_library_maker-0.0.1.dist-info/top_level.txt
galaxy_library_maker-0.0.1.dist-info/RECORD
