Metadata-Version: 2.1
Name: galaxy-library-maker
Version: 0.0.1
Summary: Traverses directories to create Galaxy libraries
Home-page: UNKNOWN
Author: Pablo Moreno
Author-email: 
License: MIT
Platform: UNKNOWN
Requires-Dist: bioblend (==0.14.0)
